huna_utils/__init__.py
huna_utils/utils.py
utils_huna/__init__.py
utils_huna/utils.py
utils_huna/utils_huna.py
utils_huna-0.1.12.dist-info/METADATA
utils_huna-0.1.12.dist-info/WHEEL
utils_huna-0.1.12.dist-info/top_level.txt
utils_huna-0.1.12.dist-info/RECORD
