Metadata-Version: 2.1
Name: utils-huna
Version: 0.1.12
Summary: HUNA helper functions
Author: Huna
